odoo/addons/sale_order_lot_selection/README.rst
odoo/addons/sale_order_lot_selection/__init__.py
odoo/addons/sale_order_lot_selection/__manifest__.py
odoo/addons/sale_order_lot_selection/demo/sale_demo.xml
odoo/addons/sale_order_lot_selection/i18n/ca.po
odoo/addons/sale_order_lot_selection/i18n/de.po
odoo/addons/sale_order_lot_selection/i18n/el_GR.po
odoo/addons/sale_order_lot_selection/i18n/es.po
odoo/addons/sale_order_lot_selection/i18n/es_ES.po
odoo/addons/sale_order_lot_selection/i18n/es_MX.po
odoo/addons/sale_order_lot_selection/i18n/es_VE.po
odoo/addons/sale_order_lot_selection/i18n/fi.po
odoo/addons/sale_order_lot_selection/i18n/fr.po
odoo/addons/sale_order_lot_selection/i18n/gl.po
odoo/addons/sale_order_lot_selection/i18n/hr.po
odoo/addons/sale_order_lot_selection/i18n/hr_HR.po
odoo/addons/sale_order_lot_selection/i18n/hu.po
odoo/addons/sale_order_lot_selection/i18n/it.po
odoo/addons/sale_order_lot_selection/i18n/nl.po
odoo/addons/sale_order_lot_selection/i18n/nl_NL.po
odoo/addons/sale_order_lot_selection/i18n/pt.po
odoo/addons/sale_order_lot_selection/i18n/pt_BR.po
odoo/addons/sale_order_lot_selection/i18n/pt_PT.po
odoo/addons/sale_order_lot_selection/i18n/ro.po
odoo/addons/sale_order_lot_selection/i18n/sale_order_lot_selection.pot
odoo/addons/sale_order_lot_selection/i18n/sk.po
odoo/addons/sale_order_lot_selection/i18n/sl.po
odoo/addons/sale_order_lot_selection/i18n/tr.po
odoo/addons/sale_order_lot_selection/i18n/tr_TR.po
odoo/addons/sale_order_lot_selection/i18n/vi_VN.po
odoo/addons/sale_order_lot_selection/i18n/zh_CN.po
odoo/addons/sale_order_lot_selection/models/__init__.py
odoo/addons/sale_order_lot_selection/models/sale_order_line.py
odoo/addons/sale_order_lot_selection/models/stock_move.py
odoo/addons/sale_order_lot_selection/readme/CONTRIBUTORS.md
odoo/addons/sale_order_lot_selection/readme/DESCRIPTION.md
odoo/addons/sale_order_lot_selection/readme/ROADMAP.md
odoo/addons/sale_order_lot_selection/readme/USAGE.md
odoo_addon_sale_order_lot_selection-18.0.1.2.4.2.dist-info/METADATA
odoo_addon_sale_order_lot_selection-18.0.1.2.4.2.dist-info/WHEEL
odoo_addon_sale_order_lot_selection-18.0.1.2.4.2.dist-info/top_level.txt
odoo_addon_sale_order_lot_selection-18.0.1.2.4.2.dist-info/RECORD
