Metadata-Version: 2.1
Name: odoo-addon-sale_order_lot_selection
Version: 18.0.1.2.4.2
Requires-Python: >=3.10
Requires-Dist: odoo-addon-stock_restrict_lot==18.0.*
Requires-Dist: odoo==18.0.*
Summary: Sale Order Lot Selection
Home-page: https://github.com/OCA/sale-workflow
License: AGPL-3
Author: Odoo Community Association (OCA), Agile Business Group
Author-email: support@odoo-community.org
Classifier: Programming Language :: Python
Classifier: Framework :: Odoo
Classifier: Framework :: Odoo :: 18.0
Classifier: License :: OSI Approved :: GNU Affero General Public License v3
